osinttool/__init__.py
osinttool/main.py
osinttool-0.1.0.dist-info/licenses/LICENSE
osinttool-0.1.0.dist-info/METADATA
osinttool-0.1.0.dist-info/WHEEL
osinttool-0.1.0.dist-info/entry_points.txt
osinttool-0.1.0.dist-info/top_level.txt
osinttool-0.1.0.dist-info/RECORD
