Metadata-Version: 2.4
Name: osinttool
Version: 0.1.0
Summary: Un outil OSINT qui affiche un message
Author-email: Baptiste <tonmail@example.com>
License: MIT
Requires-Python: >=3.8
License-File: LICENSE
Dynamic: license-file
